edumfa/__init__.py
edumfa/app.py
edumfa/babel.cfg
edumfa/config.py
edumfa/models.py
edumfa/api/__init__.py
edumfa/api/application.py
edumfa/api/audit.py
edumfa/api/auth.py
edumfa/api/before_after.py
edumfa/api/caconnector.py
edumfa/api/clienttype.py
edumfa/api/edumfaserver.py
edumfa/api/event.py
edumfa/api/machine.py
edumfa/api/machineresolver.py
edumfa/api/monitoring.py
edumfa/api/periodictask.py
edumfa/api/policy.py
edumfa/api/radiusserver.py
edumfa/api/realm.py
edumfa/api/recover.py
edumfa/api/register.py
edumfa/api/resolver.py
edumfa/api/serviceid.py
edumfa/api/smsgateway.py
edumfa/api/smtpserver.py
edumfa/api/system.py
edumfa/api/token.py
edumfa/api/tokengroup.py
edumfa/api/ttype.py
edumfa/api/user.py
edumfa/api/validate.py
edumfa/api/lib/__init__.py
edumfa/api/lib/decorators.py
edumfa/api/lib/policyhelper.py
edumfa/api/lib/postpolicy.py
edumfa/api/lib/prepolicy.py
edumfa/api/lib/utils.py
edumfa/commands/__init__.py
edumfa/commands/manage/__init__.py
edumfa/commands/manage/admin.py
edumfa/commands/manage/api.py
edumfa/commands/manage/audit.py
edumfa/commands/manage/authcache.py
edumfa/commands/manage/backup.py
edumfa/commands/manage/ca.py
edumfa/commands/manage/config.py
edumfa/commands/manage/core.py
edumfa/commands/manage/event.py
edumfa/commands/manage/helper.py
edumfa/commands/manage/hsm.py
edumfa/commands/manage/main.py
edumfa/commands/manage/policy.py
edumfa/commands/manage/realm.py
edumfa/commands/manage/resolver.py
edumfa/commands/manage/token.py
edumfa/lib/__init__.py
edumfa/lib/apps.py
edumfa/lib/audit.py
edumfa/lib/auth.py
edumfa/lib/authcache.py
edumfa/lib/caconnector.py
edumfa/lib/challenge.py
edumfa/lib/challengeresponsedecorators.py
edumfa/lib/clientapplication.py
edumfa/lib/config.py
edumfa/lib/counter.py
edumfa/lib/crypto.py
edumfa/lib/decorators.py
edumfa/lib/edumfaserver.py
edumfa/lib/error.py
edumfa/lib/event.py
edumfa/lib/framework.py
edumfa/lib/importotp.py
edumfa/lib/lifecycle.py
edumfa/lib/log.py
edumfa/lib/machine.py
edumfa-2.9.0.dist-info/licenses/AUTHORS.md
edumfa-2.9.0.dist-info/licenses/LICENSE
edumfa-2.9.0.dist-info/METADATA
edumfa-2.9.0.dist-info/WHEEL
edumfa-2.9.0.dist-info/entry_points.txt
edumfa-2.9.0.dist-info/top_level.txt
edumfa-2.9.0.dist-info/RECORD
